cili/__init__.py
cili/cleanup.py
cili/extract.py
cili/models.py
cili/util.py
cili-0.5.3.dist-info/DESCRIPTION.rst
cili-0.5.3.dist-info/METADATA
cili-0.5.3.dist-info/metadata.json
cili-0.5.3.dist-info/RECORD
cili-0.5.3.dist-info/top_level.txt
cili-0.5.3.dist-info/WHEEL
