Metadata-Version: 2.0
Name: cili
Version: 0.5.3
Summary: Eyetracking data tools based on pandas
Home-page: https://github.com/beOn/cili
Author: Ben Acland
Author-email: benacland@gmail.com
License: BSD
Keywords: eyetracking pupillometry eyelink
Platform: UNKNOWN
Classifier: Development Status :: 2 - Pre-Alpha
Classifier: Topic :: Scientific/Engineering :: Information Analysis
Classifier: License :: OSI Approved :: BSD License
Classifier: Intended Audience :: Science/Research
Requires-Dist: scipy
Requires-Dist: numexpr
Requires-Dist: tables
Requires-Dist: pandas
